cowsay/__init__.py
cowsay/__main__.py
cowsay/impl.py
wagjo_cowsay-0.0.1.dist-info/licenses/LICENSE
wagjo_cowsay-0.0.1.dist-info/METADATA
wagjo_cowsay-0.0.1.dist-info/WHEEL
wagjo_cowsay-0.0.1.dist-info/entry_points.txt
wagjo_cowsay-0.0.1.dist-info/top_level.txt
wagjo_cowsay-0.0.1.dist-info/RECORD
