Metadata-Version: 2.4
Name: wagjo-cowsay
Version: 0.0.1
Summary: Cowsay
Author-email: wagjo <wagjo@wagjo.com>
License-Expression: MIT
Project-URL: Homepage, https://github.com/wagjo/cowsay
Project-URL: Issues, https://github.com/wagjo/cowsay/issues
License-File: LICENSE
Requires-Dist: colored
Requires-Dist: ascii-announcers==0.0.2
Provides-Extra: deploy
Requires-Dist: twine; extra == "deploy"
Requires-Dist: build; extra == "deploy"
Dynamic: license-file
